README.md
setup.py
dataprojects/__init__.py
dataprojects/main.py
dataprojects/validation.py
dataprojects/wallmartclass.py
dataprojects.egg-info/PKG-INFO
dataprojects.egg-info/SOURCES.txt
dataprojects.egg-info/dependency_links.txt
dataprojects.egg-info/requires.txt
dataprojects.egg-info/top_level.txt