Metadata-Version: 2.1
Name: dataprojects
Version: 0.4
Summary: PDF invoices
Home-page: https://github.com/rajat45mishra/pdfresolver
Download-URL: https://github.com/rajat45mishra/pdfresolver.git
Author: Rajat Mishra
Author-email: rajatm@bhalariametal.com
License: MIT
Keywords: SOME,MEANINGFULL,KEYWORDS
Classifier: Development Status :: 3 - Alpha
Classifier: Intended Audience :: Developers
Classifier: Topic :: Software Development :: Build Tools
Classifier: License :: OSI Approved :: MIT License
Classifier: Programming Language :: Python :: 3
Classifier: Programming Language :: Python :: 3.4
Classifier: Programming Language :: Python :: 3.5
Classifier: Programming Language :: Python :: 3.6
